ioiopype/__init__.py
ioiopype/__version__.py
ioiopype/common/__init__.py
ioiopype/common/i_nodes/__init__.py
ioiopype/common/i_nodes/console_log.py
ioiopype/common/i_nodes/csv_logger.py
ioiopype/common/i_nodes/to_workspace.py
ioiopype/common/i_nodes/udp_sender.py
ioiopype/common/io_nodes/__init__.py
ioiopype/common/io_nodes/buffer.py
ioiopype/common/io_nodes/butterworth_filter.py
ioiopype/common/io_nodes/butterworth_filtfilt.py
ioiopype/common/io_nodes/complementary_filter.py
ioiopype/common/io_nodes/deserialize.py
ioiopype/common/io_nodes/downsample.py
ioiopype/common/io_nodes/get_range.py
ioiopype/common/io_nodes/lfhf.py
ioiopype/common/io_nodes/log.py
ioiopype/common/io_nodes/movement_detector.py
ioiopype/common/io_nodes/mux.py
ioiopype/common/io_nodes/offset_correction.py
ioiopype/common/io_nodes/operation.py
ioiopype/common/io_nodes/poincare.py
ioiopype/common/io_nodes/pwelch.py
ioiopype/common/io_nodes/serialize.py
ioiopype/common/io_nodes/sqrt.py
ioiopype/common/io_nodes/square.py
ioiopype/common/io_nodes/to_sample.py
ioiopype/common/io_nodes/transpose.py
ioiopype/common/o_nodes/__init__.py
ioiopype/common/o_nodes/ble_heart_rate.py
ioiopype/common/o_nodes/ble_heart_rate_simulator.py
ioiopype/common/o_nodes/constant.py
ioiopype/common/o_nodes/counter.py
ioiopype/common/o_nodes/csv_reader.py
ioiopype/common/o_nodes/frame.py
ioiopype/common/o_nodes/noise_generator.py
ioiopype/common/o_nodes/signal_generator.py
ioiopype/common/o_nodes/udp_receiver.py
ioiopype/common/utilities/__init__.py
ioiopype/common/utilities/butterworth.py
ioiopype/common/utilities/filter_types.py
ioiopype/common/utilities/overriding_buffer.py
ioiopype/common/utilities/realtime_clock.py
ioiopype/desktop/__init__.py
ioiopype/desktop/i_nodes/__init__.py
ioiopype/desktop/i_nodes/frame_plot.py
ioiopype/desktop/i_nodes/sample_plot.py
ioiopype/desktop/i_nodes/spectrum_plot.py
ioiopype/pattern/__init__.py
ioiopype/pattern/i_node.py
ioiopype/pattern/i_stream.py
ioiopype/pattern/io_node.py
ioiopype-0.0.14.dist-info/LICENSE
ioiopype-0.0.14.dist-info/METADATA
ioiopype-0.0.14.dist-info/WHEEL
ioiopype-0.0.14.dist-info/top_level.txt
ioiopype-0.0.14.dist-info/RECORD
