Metadata-Version: 2.1
Name: ioiopype
Version: 0.0.14
Summary: A realtime processing framework for python
Home-page: https://github.com/MartinWalchshofer/ioiopype
Author: Martin Walchshofer
Author-email: mwalchshoferyt@gmail.com
License: MIT
Classifier: Development Status :: 2 - Pre-Alpha
Classifier: License :: OSI Approved :: MIT License
Classifier: Operating System :: Microsoft :: Windows
Classifier: Operating System :: POSIX :: Linux
Classifier: Operating System :: MacOS
Classifier: Programming Language :: Python :: 3
License-File: LICENSE
